<?xml version="1.1" encoding="UTF-8"?>

<!--
 * See the NOTICE file distributed with this work for additional
 * information regarding copyright ownership.
 *
 * This is free software; you can redistribute it and/or modify it
 * under the terms of the GNU Lesser General Public License as
 * published by the Free Software Foundation; either version 2.1 of
 * the License, or (at your option) any later version.
 *
 * This software is distributed in the hope that it will be useful,
 * but WITHOUT ANY WARRANTY; without even the implied warranty of
 * MERCHANTABILITY or FITNESS FOR A PARTICULAR PURPOSE. See the GNU
 * Lesser General Public License for more details.
 *
 * You should have received a copy of the GNU Lesser General Public
 * License along with this software; if not, write to the Free
 * Software Foundation, Inc., 51 Franklin St, Fifth Floor, Boston, MA
 * 02110-1301 USA, or see the FSF site: http://www.fsf.org.
-->

<xwikidoc version="1.3" reference="Catalog.Code.CatalogPropertiesClass" locale="">
  <web>Catalog.Code</web>
  <name>CatalogPropertiesClass</name>
  <language/>
  <defaultLanguage/>
  <translation>0</translation>
  <creator>xwiki:XWiki.Admin</creator>
  <parent>WebHome</parent>
  <author>xwiki:XWiki.Admin</author>
  <contentAuthor>xwiki:XWiki.Admin</contentAuthor>
  <version>1.1</version>
  <title/>
  <comment/>
  <minorEdit>false</minorEdit>
  <syntaxId>xwiki/2.1</syntaxId>
  <hidden>false</hidden>
  <content/>
  <class>
    <name>Catalog.Code.CatalogPropertiesClass</name>
    <customClass/>
    <customMapping/>
    <defaultViewSheet/>
    <defaultEditSheet/>
    <defaultWeb/>
    <nameField/>
    <validationScript/>
    <L1>
      <customDisplay/>
      <defaultValue>1</defaultValue>
      <disabled>0</disabled>
      <displayFormType>checkbox</displayFormType>
      <displayType/>
      <hint/>
      <name>L1</name>
      <number>5</number>
      <prettyName>L1</prettyName>
      <unmodifiable>0</unmodifiable>
      <validationMessage/>
      <validationRegExp/>
      <classType>com.xpn.xwiki.objects.classes.BooleanClass</classType>
    </L1>
    <L10>
      <customDisplay/>
      <defaultValue>1</defaultValue>
      <disabled>0</disabled>
      <displayFormType>checkbox</displayFormType>
      <displayType/>
      <hint/>
      <name>L10</name>
      <number>14</number>
      <prettyName>L10</prettyName>
      <unmodifiable>0</unmodifiable>
      <validationMessage/>
      <validationRegExp/>
      <classType>com.xpn.xwiki.objects.classes.BooleanClass</classType>
    </L10>
    <L11>
      <customDisplay/>
      <defaultValue>1</defaultValue>
      <disabled>0</disabled>
      <displayFormType>checkbox</displayFormType>
      <displayType/>
      <hint/>
      <name>L11</name>
      <number>15</number>
      <prettyName>L11</prettyName>
      <unmodifiable>0</unmodifiable>
      <validationMessage/>
      <validationRegExp/>
      <classType>com.xpn.xwiki.objects.classes.BooleanClass</classType>
    </L11>
    <L12>
      <customDisplay/>
      <defaultValue>1</defaultValue>
      <disabled>0</disabled>
      <displayFormType>checkbox</displayFormType>
      <displayType/>
      <hint/>
      <name>L12</name>
      <number>16</number>
      <prettyName>L12</prettyName>
      <unmodifiable>0</unmodifiable>
      <validationMessage/>
      <validationRegExp/>
      <classType>com.xpn.xwiki.objects.classes.BooleanClass</classType>
    </L12>
    <L13>
      <customDisplay/>
      <defaultValue>1</defaultValue>
      <disabled>0</disabled>
      <displayFormType>checkbox</displayFormType>
      <displayType/>
      <hint/>
      <name>L13</name>
      <number>17</number>
      <prettyName>L13</prettyName>
      <unmodifiable>0</unmodifiable>
      <validationMessage/>
      <validationRegExp/>
      <classType>com.xpn.xwiki.objects.classes.BooleanClass</classType>
    </L13>
    <L2>
      <customDisplay/>
      <defaultValue>1</defaultValue>
      <disabled>0</disabled>
      <displayFormType>checkbox</displayFormType>
      <displayType/>
      <hint/>
      <name>L2</name>
      <number>6</number>
      <prettyName>L2</prettyName>
      <unmodifiable>0</unmodifiable>
      <validationMessage/>
      <validationRegExp/>
      <classType>com.xpn.xwiki.objects.classes.BooleanClass</classType>
    </L2>
    <L3>
      <customDisplay/>
      <defaultValue>1</defaultValue>
      <disabled>0</disabled>
      <displayFormType>checkbox</displayFormType>
      <displayType/>
      <hint/>
      <name>L3</name>
      <number>7</number>
      <prettyName>L3</prettyName>
      <unmodifiable>0</unmodifiable>
      <validationMessage/>
      <validationRegExp/>
      <classType>com.xpn.xwiki.objects.classes.BooleanClass</classType>
    </L3>
    <L4>
      <customDisplay/>
      <defaultValue>1</defaultValue>
      <disabled>0</disabled>
      <displayFormType>checkbox</displayFormType>
      <displayType/>
      <hint/>
      <name>L4</name>
      <number>8</number>
      <prettyName>L4</prettyName>
      <unmodifiable>0</unmodifiable>
      <validationMessage/>
      <validationRegExp/>
      <classType>com.xpn.xwiki.objects.classes.BooleanClass</classType>
    </L4>
    <L5>
      <customDisplay/>
      <defaultValue>1</defaultValue>
      <disabled>0</disabled>
      <displayFormType>checkbox</displayFormType>
      <displayType/>
      <hint/>
      <name>L5</name>
      <number>9</number>
      <prettyName>L5</prettyName>
      <unmodifiable>0</unmodifiable>
      <validationMessage/>
      <validationRegExp/>
      <classType>com.xpn.xwiki.objects.classes.BooleanClass</classType>
    </L5>
    <L6>
      <customDisplay/>
      <defaultValue>1</defaultValue>
      <disabled>0</disabled>
      <displayFormType>checkbox</displayFormType>
      <displayType/>
      <hint/>
      <name>L6</name>
      <number>10</number>
      <prettyName>L6</prettyName>
      <unmodifiable>0</unmodifiable>
      <validationMessage/>
      <validationRegExp/>
      <classType>com.xpn.xwiki.objects.classes.BooleanClass</classType>
    </L6>
    <L7>
      <customDisplay/>
      <defaultValue>1</defaultValue>
      <disabled>0</disabled>
      <displayFormType>checkbox</displayFormType>
      <displayType/>
      <hint/>
      <name>L7</name>
      <number>11</number>
      <prettyName>L7</prettyName>
      <unmodifiable>0</unmodifiable>
      <validationMessage/>
      <validationRegExp/>
      <classType>com.xpn.xwiki.objects.classes.BooleanClass</classType>
    </L7>
    <L8>
      <customDisplay/>
      <defaultValue>1</defaultValue>
      <disabled>0</disabled>
      <displayFormType>checkbox</displayFormType>
      <displayType/>
      <hint/>
      <name>L8</name>
      <number>12</number>
      <prettyName>L8</prettyName>
      <unmodifiable>0</unmodifiable>
      <validationMessage/>
      <validationRegExp/>
      <classType>com.xpn.xwiki.objects.classes.BooleanClass</classType>
    </L8>
    <L9>
      <customDisplay/>
      <defaultValue>1</defaultValue>
      <disabled>0</disabled>
      <displayFormType>checkbox</displayFormType>
      <displayType/>
      <hint/>
      <name>L9</name>
      <number>13</number>
      <prettyName>L9</prettyName>
      <unmodifiable>0</unmodifiable>
      <validationMessage/>
      <validationRegExp/>
      <classType>com.xpn.xwiki.objects.classes.BooleanClass</classType>
    </L9>
    <attendances>
      <customDisplay/>
      <defaultValue>1</defaultValue>
      <disabled>0</disabled>
      <displayFormType>checkbox</displayFormType>
      <displayType/>
      <hint/>
      <name>attendances</name>
      <number>4</number>
      <prettyName>attendances</prettyName>
      <unmodifiable>0</unmodifiable>
      <validationMessage/>
      <validationRegExp/>
      <classType>com.xpn.xwiki.objects.classes.BooleanClass</classType>
    </attendances>
    <bonus>
      <customDisplay/>
      <defaultValue>1</defaultValue>
      <disabled>0</disabled>
      <displayFormType>checkbox</displayFormType>
      <displayType/>
      <hint/>
      <name>bonus</name>
      <number>18</number>
      <prettyName>bonus</prettyName>
      <unmodifiable>0</unmodifiable>
      <validationMessage/>
      <validationRegExp/>
      <classType>com.xpn.xwiki.objects.classes.BooleanClass</classType>
    </bonus>
    <doctitle>
      <customDisplay/>
      <defaultValue>1</defaultValue>
      <disabled>0</disabled>
      <displayFormType>checkbox</displayFormType>
      <displayType/>
      <hint/>
      <name>doctitle</name>
      <number>1</number>
      <prettyName>doctitle</prettyName>
      <unmodifiable>0</unmodifiable>
      <validationMessage/>
      <validationRegExp/>
      <classType>com.xpn.xwiki.objects.classes.BooleanClass</classType>
    </doctitle>
    <exam>
      <customDisplay/>
      <defaultValue>1</defaultValue>
      <disabled>0</disabled>
      <displayFormType>checkbox</displayFormType>
      <displayType/>
      <hint/>
      <name>exam</name>
      <number>20</number>
      <prettyName>exam</prettyName>
      <unmodifiable>0</unmodifiable>
      <validationMessage/>
      <validationRegExp/>
      <classType>com.xpn.xwiki.objects.classes.BooleanClass</classType>
    </exam>
    <lab>
      <customDisplay/>
      <defaultValue>1</defaultValue>
      <disabled>0</disabled>
      <displayFormType>checkbox</displayFormType>
      <displayType/>
      <hint/>
      <name>lab</name>
      <number>21</number>
      <prettyName>lab</prettyName>
      <unmodifiable>0</unmodifiable>
      <validationMessage/>
      <validationRegExp/>
      <classType>com.xpn.xwiki.objects.classes.BooleanClass</classType>
    </lab>
    <premiere>
      <customDisplay/>
      <defaultValue>1</defaultValue>
      <disabled>0</disabled>
      <displayFormType>checkbox</displayFormType>
      <displayType/>
      <hint/>
      <name>premiere</name>
      <number>19</number>
      <prettyName>premiere</prettyName>
      <unmodifiable>0</unmodifiable>
      <validationMessage/>
      <validationRegExp/>
      <classType>com.xpn.xwiki.objects.classes.BooleanClass</classType>
    </premiere>
    <reExam>
      <customDisplay/>
      <defaultValue>1</defaultValue>
      <disabled>0</disabled>
      <displayFormType>checkbox</displayFormType>
      <displayType/>
      <hint/>
      <name>reExam</name>
      <number>24</number>
      <prettyName>reExam</prettyName>
      <unmodifiable>0</unmodifiable>
      <validationMessage/>
      <validationRegExp/>
      <classType>com.xpn.xwiki.objects.classes.BooleanClass</classType>
    </reExam>
    <registrationID>
      <customDisplay/>
      <defaultValue>0</defaultValue>
      <disabled>0</disabled>
      <displayFormType>checkbox</displayFormType>
      <displayType/>
      <hint/>
      <name>registrationID</name>
      <number>2</number>
      <prettyName>registrationID</prettyName>
      <unmodifiable>0</unmodifiable>
      <validationMessage/>
      <validationRegExp/>
      <classType>com.xpn.xwiki.objects.classes.BooleanClass</classType>
    </registrationID>
    <situatie_finala>
      <customDisplay/>
      <defaultValue>1</defaultValue>
      <disabled>0</disabled>
      <displayFormType>checkbox</displayFormType>
      <displayType/>
      <hint/>
      <name>situatie_finala</name>
      <number>23</number>
      <prettyName>situatie_finala</prettyName>
      <unmodifiable>0</unmodifiable>
      <validationMessage/>
      <validationRegExp/>
      <classType>com.xpn.xwiki.objects.classes.BooleanClass</classType>
    </situatie_finala>
    <studentGroup>
      <customDisplay/>
      <defaultValue>1</defaultValue>
      <disabled>0</disabled>
      <displayFormType>checkbox</displayFormType>
      <displayType/>
      <hint/>
      <name>studentGroup</name>
      <number>3</number>
      <prettyName>studentGroup</prettyName>
      <unmodifiable>0</unmodifiable>
      <validationMessage/>
      <validationRegExp/>
      <classType>com.xpn.xwiki.objects.classes.BooleanClass</classType>
    </studentGroup>
    <total>
      <customDisplay/>
      <defaultValue>1</defaultValue>
      <disabled>0</disabled>
      <displayFormType>checkbox</displayFormType>
      <displayType/>
      <hint/>
      <name>total</name>
      <number>22</number>
      <prettyName>total</prettyName>
      <unmodifiable>0</unmodifiable>
      <validationMessage/>
      <validationRegExp/>
      <classType>com.xpn.xwiki.objects.classes.BooleanClass</classType>
    </total>
  </class>
</xwikidoc>
